telegram_jellyfin_bot/__init__.py
telegram_jellyfin_bot/bot.py
telegram_jellyfin_bot-0.1.2.dist-info/LICENSE
telegram_jellyfin_bot-0.1.2.dist-info/METADATA
telegram_jellyfin_bot-0.1.2.dist-info/WHEEL
telegram_jellyfin_bot-0.1.2.dist-info/entry_points.txt
telegram_jellyfin_bot-0.1.2.dist-info/top_level.txt
telegram_jellyfin_bot-0.1.2.dist-info/RECORD
