Metadata-Version: 2.1
Name: telegram_jellyfin_bot
Version: 0.1.2
Summary: A Telegram bot to download videos to a Jellyfin server.
Home-page: https://github.com/oritor91/telegram_jellyfin_bot
Author: Your Name
Author-email: your.email@example.com
Classifier: Programming Language :: Python :: 3
Classifier: License :: OSI Approved :: MIT License
Classifier: Operating System :: OS Independent
Requires-Python: >=3.6
License-File: LICENSE
Requires-Dist: python-telegram-bot >=13.0
Requires-Dist: yt-dlp
Requires-Dist: pyrogram
Requires-Dist: tgcrypto
Requires-Dist: pydantic
